heareval/__init__.py
heareval/gpu_max_mem.py
heareval/multigpu.py
heareval/score.py
heareval/embeddings/__init__.py
heareval/embeddings/runner.py
heareval/embeddings/task_embeddings.py
heareval/predictions/__init__.py
heareval/predictions/runner.py
heareval/predictions/task_predictions.py
heareval-2021.1.3.dist-info/LICENSE
heareval-2021.1.3.dist-info/METADATA
heareval-2021.1.3.dist-info/WHEEL
heareval-2021.1.3.dist-info/top_level.txt
heareval-2021.1.3.dist-info/RECORD
