Metadata-Version: 2.1
Name: heareval
Version: 2021.1.3
Summary: Holistic Evaluation of Audio Representations (HEAR) 2021 -- Evaluation Kit
Home-page: https://github.com/hearbenchmark/hear-eval-kit
Download-URL: https://github.com/hearbenchmark/hear-eval-kit
Author: 
Author-email: 
License: Apache-2.0
Project-URL: Bug Tracker, https://github.com/hearbenchmark/hear-eval-kit/issues
Project-URL: Source Code, https://github.com/hearbenchmark/hear-eval-kit
Requires-Python: >=3.7
License-File: LICENSE
Requires-Dist: click
Requires-Dist: dcase-util
Requires-Dist: intervaltree
Requires-Dist: more-itertools
Requires-Dist: numpy (==1.19.2)
Requires-Dist: pandas
Requires-Dist: pynvml
Requires-Dist: pytorch-lightning (>=1.6)
Requires-Dist: python-slugify
Requires-Dist: sed-eval
Requires-Dist: soundfile
Requires-Dist: spotty
Requires-Dist: tensorflow (>=2.0)
Requires-Dist: torch
Requires-Dist: torchinfo
Requires-Dist: tqdm
Requires-Dist: scikit-learn (>=0.24.2)
Requires-Dist: numba (==0.48)
Provides-Extra: dev
Requires-Dist: pre-commit ; extra == 'dev'
Requires-Dist: black ; extra == 'dev'
Requires-Dist: pytest ; extra == 'dev'
Requires-Dist: pytest-cov ; extra == 'dev'
Requires-Dist: pytest-env ; extra == 'dev'
Provides-Extra: test
Requires-Dist: pytest ; extra == 'test'
Requires-Dist: pytest-cov ; extra == 'test'
Requires-Dist: pytest-env ; extra == 'test'
